README.rst
setup.py
kMer.egg-info/PKG-INFO
kMer.egg-info/SOURCES.txt
kMer.egg-info/dependency_links.txt
kMer.egg-info/requires.txt
kMer.egg-info/top_level.txt
k_mer/__init__.py
k_mer/distr.py